function_burger/__init__.py
function_burger/function_burger.py
function_burger-1.1.0.dist-info/LICENSE
function_burger-1.1.0.dist-info/METADATA
function_burger-1.1.0.dist-info/WHEEL
function_burger-1.1.0.dist-info/top_level.txt
function_burger-1.1.0.dist-info/RECORD
