Metadata-Version: 2.1
Name: function-burger
Version: 1.1.0
Summary: function-burger🍔 is a library that outputs logs before and(or) after a function.
Home-page: https://github.com/MamedenQ/function-burger
Download-URL: https://github.com/MamedenQ/function-burger
Author: shinya_sun_sun
Author-email: dynabook.miu@gmail.com
Maintainer: shinya_sun_sun
Maintainer-email: dynabook.miu@gmail.com
License: MIT License
Classifier: License :: OSI Approved :: MIT License
Classifier: Programming Language :: Python :: 3
Classifier: Programming Language :: Python :: 3.7
Classifier: Programming Language :: Python :: 3.8
Classifier: Programming Language :: Python :: 3.9
Classifier: Programming Language :: Python :: 3.10
Requires-Python: >=3.7
License-File: LICENSE
Provides-Extra: testing
Requires-Dist: pytest ; extra == 'testing'
Requires-Dist: pytest-cov ; extra == 'testing'
